itk/_KrcahSheetnessPython.so
itk/itkKrcahSheetnessFeatureImageFilterPython.py
itk/KrcahSheetnessPython.py
itk/Configuration/KrcahSheetnessConfig.py
itk_krcahsheetness-0.1.0.dist-info/RECORD
itk_krcahsheetness-0.1.0.dist-info/DESCRIPTION.rst
itk_krcahsheetness-0.1.0.dist-info/metadata.json
itk_krcahsheetness-0.1.0.dist-info/METADATA
itk_krcahsheetness-0.1.0.dist-info/WHEEL
itk_krcahsheetness-0.1.0.dist-info/top_level.txt
